testrankhist/__init__.py
testrankhist/funcs.py
testrankhist-0.12.dist-info/LICENSE
testrankhist-0.12.dist-info/METADATA
testrankhist-0.12.dist-info/WHEEL
testrankhist-0.12.dist-info/top_level.txt
testrankhist-0.12.dist-info/RECORD
