Metadata-Version: 2.1
Name: testrankhist
Version: 0.12
Summary: Statisctical tests for rank histograms
Home-page: https://github.com/tourniert/TestRankHist
Author: tourniert
Author-email: theo.tournier@meteo.fr
License: MIT
Project-URL: Bug Tracker, https://github.com/tourniert/TestRankHist/issues
Platform: UNKNOWN
Classifier: Development Status :: 3 - Alpha
Classifier: License :: OSI Approved :: MIT License
Classifier: Operating System :: OS Independent
Classifier: Intended Audience :: Science/Research
Classifier: Programming Language :: Python :: 3
Classifier: Topic :: Scientific/Engineering
License-File: LICENSE
Requires-Dist: numpy
Requires-Dist: scipy
Requires-Dist: matplotlib
